[
  {
    "ean": "7798222460018",
    "nombre": "formitas de soja latina x 400 gr.",
    "categoria": "Congelados",
    "precio_antes": 1769.0,
    "precio_hoy": 4217.0,
    "diff_abs": 2448.0,
    "diff_pct": 138.38
  },
  {
    "ean": "7790387011852",
    "nombre": "mate cocido taragui ni$os vainilla y miel x 20 saq",
    "categoria": "Perfumeria",
    "precio_antes": 1529.0,
    "precio_hoy": 2621.0,
    "diff_abs": 1092.0,
    "diff_pct": 71.42
  },
  {
    "ean": "80052487",
    "nombre": "bombon raffaello x 3 unidades",
    "categoria": "Almacen",
    "precio_antes": 1829.0,
    "precio_hoy": 3049.0,
    "diff_abs": 1220.0,
    "diff_pct": 66.7
  },
  {
    "ean": "2025590000009",
    "nombre": "puchero caracu ternera x kg.",
    "categoria": "Carniceria",
    "precio_antes": 4800.0,
    "precio_hoy": 7900.0,
    "diff_abs": 3100.0,
    "diff_pct": 64.58
  },
  {
    "ean": "2025600000005",
    "nombre": "puchero de aguja ternera x kg.",
    "categoria": "Carniceria",
    "precio_antes": 4800.0,
    "precio_hoy": 7900.0,
    "diff_abs": 3100.0,
    "diff_pct": 64.58
  },
  {
    "ean": "7790360982537",
    "nombre": "milanesitas swift x 400 gm carne",
    "categoria": "Congelados",
    "precio_antes": 5440.0,
    "precio_hoy": 8718.0,
    "diff_abs": 3278.0,
    "diff_pct": 60.26
  },
  {
    "ean": "7500810034330",
    "nombre": "snack takis fuego x 140 gr.",
    "categoria": "Almacen",
    "precio_antes": 2829.0,
    "precio_hoy": 4453.0,
    "diff_abs": 1624.0,
    "diff_pct": 57.41
  },
  {
    "ean": "7500810034354",
    "nombre": "snack takis original x 140 gr.",
    "categoria": "Almacen",
    "precio_antes": 2829.0,
    "precio_hoy": 4453.0,
    "diff_abs": 1624.0,
    "diff_pct": 57.41
  },
  {
    "ean": "7500810041741",
    "nombre": "snack takis x 140 gm intense",
    "categoria": "Almacen",
    "precio_antes": 2829.0,
    "precio_hoy": 4453.0,
    "diff_abs": 1624.0,
    "diff_pct": 57.41
  },
  {
    "ean": "7500810034347",
    "nombre": "snack takis xplosion x 140 gr.",
    "categoria": "Almacen",
    "precio_antes": 2829.0,
    "precio_hoy": 4453.0,
    "diff_abs": 1624.0,
    "diff_pct": 57.41
  },
  {
    "ean": "7500810034361",
    "nombre": "snack takis fuego x 85 gr.",
    "categoria": "Almacen",
    "precio_antes": 1769.0,
    "precio_hoy": 2779.0,
    "diff_abs": 1010.0,
    "diff_pct": 57.09
  },
  {
    "ean": "7500810034477",
    "nombre": "snack takis original x 85 gr.",
    "categoria": "Almacen",
    "precio_antes": 1769.0,
    "precio_hoy": 2779.0,
    "diff_abs": 1010.0,
    "diff_pct": 57.09
  },
  {
    "ean": "7500810041734",
    "nombre": "snack takis x 85 gm intense",
    "categoria": "Almacen",
    "precio_antes": 1769.0,
    "precio_hoy": 2779.0,
    "diff_abs": 1010.0,
    "diff_pct": 57.09
  },
  {
    "ean": "7898024397151",
    "nombre": "bombones ferrero collection x 77 gm",
    "categoria": "Almacen",
    "precio_antes": 7779.0,
    "precio_hoy": 12108.0,
    "diff_abs": 4329.0,
    "diff_pct": 55.65
  },
  {
    "ean": "8000500232057",
    "nombre": "bombones rafaello x 9 unid.",
    "categoria": "Almacen",
    "precio_antes": 5339.0,
    "precio_hoy": 8303.0,
    "diff_abs": 2964.0,
    "diff_pct": 55.52
  },
  {
    "ean": "7790070040039",
    "nombre": "pizza sibarita mozzarella x 940 gr.",
    "categoria": "Congelados",
    "precio_antes": 14479.0,
    "precio_hoy": 22348.0,
    "diff_abs": 7869.0,
    "diff_pct": 54.35
  },
  {
    "ean": "7790070431554",
    "nombre": "arroz gallo sabores del mundo x 240 gr. curry asia",
    "categoria": "Almacen",
    "precio_antes": 2369.0,
    "precio_hoy": 3637.0,
    "diff_abs": 1268.0,
    "diff_pct": 53.52
  },
  {
    "ean": "7790070231956",
    "nombre": "aceto balsamico lira reduccion x 250 ml.",
    "categoria": "Almacen",
    "precio_antes": 2769.0,
    "precio_hoy": 4232.0,
    "diff_abs": 1463.0,
    "diff_pct": 52.83
  },
  {
    "ean": "7898024395232",
    "nombre": "pasta de avellanas y chocolate nutella x 140 gr.",
    "categoria": "Perfumeria",
    "precio_antes": 3169.0,
    "precio_hoy": 4738.0,
    "diff_abs": 1569.0,
    "diff_pct": 49.51
  },
  {
    "ean": "7790070103314",
    "nombre": "alfajor chocoarroz 6 x 36 gm dulce de leche",
    "categoria": "Almacen",
    "precio_antes": 6269.0,
    "precio_hoy": 9284.0,
    "diff_abs": 3015.0,
    "diff_pct": 48.09
  }
]