[
  {
    "ean": "2020920000001",
    "nombre": "lechuga mantecosa x kg.",
    "categoria": "Frutas Y Verduras",
    "precio_antes": 5990.0,
    "precio_hoy": 6990.0,
    "diff_abs": 1000.0,
    "diff_pct": 16.69
  },
  {
    "ean": "2020960000009",
    "nombre": "lechuga repollada x kg.",
    "categoria": "Frutas Y Verduras",
    "precio_antes": 5990.0,
    "precio_hoy": 6990.0,
    "diff_abs": 1000.0,
    "diff_pct": 16.69
  },
  {
    "ean": "2021140000000",
    "nombre": "mandarina nova x kilo",
    "categoria": "Frutas Y Verduras",
    "precio_antes": 1290.0,
    "precio_hoy": 1490.0,
    "diff_abs": 200.0,
    "diff_pct": 15.5
  },
  {
    "ean": "2700001617969",
    "nombre": "repasador",
    "categoria": "Limpieza",
    "precio_antes": 1914.0,
    "precio_hoy": 2095.0,
    "diff_abs": 181.0,
    "diff_pct": 9.46
  },
  {
    "ean": "7798105226731",
    "nombre": "toalla bouquet aamrilla x 45 x 90 cm",
    "categoria": "Limpieza",
    "precio_antes": 6642.9,
    "precio_hoy": 6904.0,
    "diff_abs": 261.1,
    "diff_pct": 3.93
  },
  {
    "ean": "7798105224386",
    "nombre": "toalla bouquet",
    "categoria": "Limpieza",
    "precio_antes": 6642.9,
    "precio_hoy": 6904.0,
    "diff_abs": 261.1,
    "diff_pct": 3.93
  },
  {
    "ean": "7790742324108",
    "nombre": "queso unt finalndia mas liviano x 290 gr sin sal",
    "categoria": "Lacteos Y Frescos",
    "precio_antes": 5019.0,
    "precio_hoy": 5019.0,
    "diff_abs": 0.0,
    "diff_pct": 0.0
  },
  {
    "ean": "2017380000009",
    "nombre": "queso tybo descremado la paulina x kg.",
    "categoria": "Lacteos Y Frescos",
    "precio_antes": 17553.0,
    "precio_hoy": 17553.0,
    "diff_abs": 0.0,
    "diff_pct": 0.0
  },
  {
    "ean": "2010620000005",
    "nombre": "queso tremblay por salut light x kilo",
    "categoria": "Lacteos Y Frescos",
    "precio_antes": 14449.0,
    "precio_hoy": 14449.0,
    "diff_abs": 0.0,
    "diff_pct": 0.0
  },
  {
    "ean": "7793913001013",
    "nombre": "queso tregar mascarpone x 200 gr.",
    "categoria": "Lacteos Y Frescos",
    "precio_antes": 3663.0,
    "precio_hoy": 3663.0,
    "diff_abs": 0.0,
    "diff_pct": 0.0
  },
  {
    "ean": "2010680000007",
    "nombre": "queso sardo tremblay x kg.",
    "categoria": "Lacteos Y Frescos",
    "precio_antes": 26428.0,
    "precio_hoy": 26428.0,
    "diff_abs": 0.0,
    "diff_pct": 0.0
  },
  {
    "ean": "2024350000006",
    "nombre": "queso sardo tremblay trozado x kg.",
    "categoria": "Lacteos Y Frescos",
    "precio_antes": 31901.0,
    "precio_hoy": 31901.0,
    "diff_abs": 0.0,
    "diff_pct": 0.0
  },
  {
    "ean": "2011010000001",
    "nombre": "queso sardo rosalat x kg.",
    "categoria": "Lacteos Y Frescos",
    "precio_antes": 23536.0,
    "precio_hoy": 23536.0,
    "diff_abs": 0.0,
    "diff_pct": 0.0
  },
  {
    "ean": "7794990000012",
    "nombre": "queso untable la paulina port salut light x 190 g.",
    "categoria": "Lacteos Y Frescos",
    "precio_antes": 2367.0,
    "precio_hoy": 2367.0,
    "diff_abs": 0.0,
    "diff_pct": 0.0
  },
  {
    "ean": "7794990878925",
    "nombre": "queso untable la paulina jamon x 190 gr.",
    "categoria": "Lacteos Y Frescos",
    "precio_antes": 2367.0,
    "precio_hoy": 2367.0,
    "diff_abs": 0.0,
    "diff_pct": 0.0
  },
  {
    "ean": "7794990878871",
    "nombre": "queso untable la paulina fontina x 190 gr.",
    "categoria": "Lacteos Y Frescos",
    "precio_antes": 2367.0,
    "precio_hoy": 2367.0,
    "diff_abs": 0.0,
    "diff_pct": 0.0
  },
  {
    "ean": "7794990878932",
    "nombre": "queso untable la paulina clasico x 190 gr.",
    "categoria": "Lacteos Y Frescos",
    "precio_antes": 2367.0,
    "precio_hoy": 2367.0,
    "diff_abs": 0.0,
    "diff_pct": 0.0
  },
  {
    "ean": "7794990879526",
    "nombre": "queso untable la paulina cheddar x 190 gr.",
    "categoria": "Lacteos Y Frescos",
    "precio_antes": 2367.0,
    "precio_hoy": 2367.0,
    "diff_abs": 0.0,
    "diff_pct": 0.0
  },
  {
    "ean": "7794990878888",
    "nombre": "queso untable la paulina azul x 190 gr.",
    "categoria": "Lacteos Y Frescos",
    "precio_antes": 2367.0,
    "precio_hoy": 2367.0,
    "diff_abs": 0.0,
    "diff_pct": 0.0
  },
  {
    "ean": "7794990879823",
    "nombre": "queso untable la paulina 4 quesos x 190 gr.",
    "categoria": "Lacteos Y Frescos",
    "precio_antes": 2367.0,
    "precio_hoy": 2367.0,
    "diff_abs": 0.0,
    "diff_pct": 0.0
  }
]