{
  "fecha": "20260323",
  "total_productos": 5699,
  "variacion_dia": -0.0,
  "variacion_7d": 0.5,
  "variacion_mes": 1.84,
  "variacion_anio": null,
  "categorias_dia": [
    {
      "categoria": "Bebidas",
      "variacion_pct_promedio": 0.0,
      "productos_subieron": 0,
      "productos_bajaron": 0,
      "total_productos": 1264
    },
    {
      "categoria": "Frescos",
      "variacion_pct_promedio": -0.02,
      "productos_subieron": 0,
      "productos_bajaron": 1,
      "total_productos": 1141
    },
    {
      "categoria": "Congelados",
      "variacion_pct_promedio": 0.0,
      "productos_subieron": 0,
      "productos_bajaron": 0,
      "total_productos": 202
    },
    {
      "categoria": "Limpieza",
      "variacion_pct_promedio": 0.0,
      "productos_subieron": 0,
      "productos_bajaron": 0,
      "total_productos": 674
    },
    {
      "categoria": "Cuidado Personal",
      "variacion_pct_promedio": 0.0,
      "productos_subieron": 0,
      "productos_bajaron": 0,
      "total_productos": 826
    },
    {
      "categoria": "Almacen",
      "variacion_pct_promedio": 0.0,
      "productos_subieron": 0,
      "productos_bajaron": 0,
      "total_productos": 1592
    }
  ],
  "ranking_baja_dia": [
    {
      "ean": "7794080000212",
      "nombre": "tapa para pascualina la morocha hojaldre x 2 unid.",
      "categoria": "Lacteos Y Frescos",
      "precio_antes": 1667.0,
      "precio_hoy": 1249.0,
      "diff_abs": -418.0,
      "diff_pct": -25.07
    },
    {
      "ean": "7790411001521",
      "nombre": "yerba rosamonte suave plus x 500 gr.",
      "categoria": "Perfumeria",
      "precio_antes": 2179.0,
      "precio_hoy": 2179.0,
      "diff_abs": 0.0,
      "diff_pct": 0.0
    },
    {
      "ean": "7790411001378",
      "nombre": "yerba rosamonte premium caja x 500 gr",
      "categoria": "Perfumeria",
      "precio_antes": 5868.0,
      "precio_hoy": 5868.0,
      "diff_abs": 0.0,
      "diff_pct": 0.0
    },
    {
      "ean": "7790411000029",
      "nombre": "yerba rosamonte especial x 500 gr.",
      "categoria": "Perfumeria",
      "precio_antes": 3069.0,
      "precio_hoy": 3069.0,
      "diff_abs": 0.0,
      "diff_pct": 0.0
    },
    {
      "ean": "7790411000012",
      "nombre": "yerba rosamonte especial x 1 kg.",
      "categoria": "Perfumeria",
      "precio_antes": 5849.0,
      "precio_hoy": 5849.0,
      "diff_abs": 0.0,
      "diff_pct": 0.0
    },
    {
      "ean": "7790411000814",
      "nombre": "yerba rosamonte despalada x 500 gr.",
      "categoria": "Perfumeria",
      "precio_antes": 2824.0,
      "precio_hoy": 2824.0,
      "diff_abs": 0.0,
      "diff_pct": 0.0
    },
    {
      "ean": "7798028021581",
      "nombre": "yerba pajaro azul premium x 500 gr",
      "categoria": "Perfumeria",
      "precio_antes": 2323.0,
      "precio_hoy": 2323.0,
      "diff_abs": 0.0,
      "diff_pct": 0.0
    },
    {
      "ean": "7798028021611",
      "nombre": "yerba pajaro azul premium x 1kg",
      "categoria": "Perfumeria",
      "precio_antes": 4572.0,
      "precio_hoy": 4572.0,
      "diff_abs": 0.0,
      "diff_pct": 0.0
    },
    {
      "ean": "7790070100375",
      "nombre": "yerba nobleza gaucha x 500 gr cimarron",
      "categoria": "Perfumeria",
      "precio_antes": 1769.0,
      "precio_hoy": 1769.0,
      "diff_abs": 0.0,
      "diff_pct": 0.0
    },
    {
      "ean": "7790070100382",
      "nombre": "yerba nobleza gaucha x 1 kg cimarron",
      "categoria": "Perfumeria",
      "precio_antes": 3349.0,
      "precio_hoy": 3349.0,
      "diff_abs": 0.0,
      "diff_pct": 0.0
    }
  ],
  "productos_subieron_dia": 0,
  "productos_bajaron_dia": 1,
  "productos_sin_cambio_dia": 5698
}